LICENSE.txt
MANIFEST.in
Makefile
README.md
README.rst
base.mk
default.config
mem-incr.hex
setup.cfg
setup.py
c_lib/cma.h
c_lib/ipgen.h
c_lib/umem.h
examples/Makefile
include/ipgen.v
ipgen/__init__.py
ipgen/ipgen.py
ipgen/run_ipgen.py
ipgen.egg-info/PKG-INFO
ipgen.egg-info/SOURCES.txt
ipgen.egg-info/dependency_links.txt
ipgen.egg-info/entry_points.txt
ipgen.egg-info/requires.txt
ipgen.egg-info/top_level.txt
ipgen/rtl_converter/__init__.py
ipgen/rtl_converter/convertvisitor.py
ipgen/rtl_converter/interfaces.py
ipgen/rtl_converter/rtl_converter.py
ipgen/rtl_converter/run_rtl_converter.py
ipgen/template/Makefile.txt
ipgen/template/__init__.py
ipgen/template/avalon_lite_master_interface.v
ipgen/template/avalon_lite_slave_interface.v
ipgen/template/avalon_master_fifo.v
ipgen/template/avalon_master_interface.v
ipgen/template/avalon_slave_interface.v
ipgen/template/axi_lite_master_interface.v
ipgen/template/axi_lite_slave_interface.v
ipgen/template/axi_master_fifo.v
ipgen/template/axi_master_interface.v
ipgen/template/axi_slave_interface.v
ipgen/template/bd.tcl
ipgen/template/ipgen.v
ipgen/template/ipxact.xdc
ipgen/template/mpd.txt
ipgen/template/mui.txt
ipgen/template/node_avalon.txt
ipgen/template/node_axi.txt
ipgen/template/node_general.txt
ipgen/template/pao.txt
ipgen/template/pcore_tcl.tcl
ipgen/template/qsys_tcl.txt
ipgen/template/test_ipgen_avalon.txt
ipgen/template/test_ipgen_axi.txt
ipgen/template/xgui_tcl.txt
ipgen/utils/__init__.py
ipgen/utils/componentgen.py
ipgen/utils/version.py
tests/Makefile
tests/led/Makefile
tests/led/led.v
tests/led/testbench.v
tests/led/sw/ipgen.h
tests/led/sw/led.sh
tests/led/sw/main.c
tests/led/sw/umem.h
tests/memcpy/Makefile
tests/memcpy/memcpy.v
tests/memcpy/testbench.v
tests/memcpy/sw/ipgen.h
tests/memcpy/sw/main.c
tests/memcpy/sw/umem.h
tests/not_found/Makefile
tests/not_found/testbench.v
tests/not_found/userlogic.v