Metadata-Version: 1.0
Name: ipgen
Version: 1.0.0
Summary: IP-core package generator for AXI4/Avalon
Home-page: https://github.com/PyHDI/ipgen
Author: Shinya Takamaeda-Yamazaki
Author-email: UNKNOWN
License: Apache License 2.0
Keywords: FPGA,Verilog HDL,IP-core,IP-XACT,AMBA AXI4,Avalon
Platform: UNKNOWN
